nonlinshrink/__init__.py
nonlinshrink/nonlinshrink.py
nonlinshrink/test/__init__.py
nonlinshrink/test/test_analytic_shrinkage.py
tests/__init__.py
tests/test_analytic_shrinkage.py
nonlinshrink-0.7.dist-info/METADATA
nonlinshrink-0.7.dist-info/WHEEL
nonlinshrink-0.7.dist-info/top_level.txt
nonlinshrink-0.7.dist-info/RECORD
