Metadata-Version: 2.1
Name: nonlinshrink
Version: 0.7
Summary: Non-Linear Shrinkage Estimator from Ledoit and Wolf (2018) 
Home-page: https://github.com/matzhaugen/analytic_shrinkage
Author: Matz Haugen
Author-email: matzhaugen@gmail.com
License: UNKNOWN
Platform: UNKNOWN
Classifier: Programming Language :: Python :: 3
Classifier: License :: OSI Approved :: MIT License
Classifier: Operating System :: OS Independent
